README
ez_setup.py
setup.py
django_mollom.egg-info/PKG-INFO
django_mollom.egg-info/SOURCES.txt
django_mollom.egg-info/dependency_links.txt
django_mollom.egg-info/top_level.txt
mollom/__init__.py
mollom/fields.py
mollom/forms.py
mollom/models.py
mollom/tests.py
mollom/views.py
mollom/widgets.py