Metadata-Version: 1.0
Name: django-mollom
Version: 0.1.1
Summary: A Django wrapper app for the PyMollom module.
Home-page: https://github.com/marconi/django-mollom/
Author: Marconi Moreto
Author-email: caketoad@gmail.com
License: UNKNOWN
Platform: UNKNOWN
